attrdict2/__init__.py
attrdict2/default.py
attrdict2/dictionary.py
attrdict2/mapping.py
attrdict2/merge.py
attrdict2/mixins.py
attrdict2-2.0.2.dist-info/LICENSE
attrdict2-2.0.2.dist-info/METADATA
attrdict2-2.0.2.dist-info/WHEEL
attrdict2-2.0.2.dist-info/top_level.txt
attrdict2-2.0.2.dist-info/zip-safe
attrdict2-2.0.2.dist-info/RECORD
